eth_vertigo/__init__.py
eth_vertigo/cli/__init__.py
eth_vertigo/cli/main.py
eth_vertigo/core/__init__.py
eth_vertigo/core/campaign.py
eth_vertigo/core/filter.py
eth_vertigo/core/mutation.py
eth_vertigo/core/suggest.py
eth_vertigo/core/filters/__init__.py
eth_vertigo/core/filters/exclude_filter.py
eth_vertigo/core/filters/sample_filter.py
eth_vertigo/core/network/__init__.py
eth_vertigo/core/network/ganache.py
eth_vertigo/core/network/pool.py
eth_vertigo/core/templates/mutation_template.jinja2
eth_vertigo/core/templates/report_template.jinja2
eth_vertigo/incremental/__init__.py
eth_vertigo/incremental/record.py
eth_vertigo/incremental/store.py
eth_vertigo/incremental/suggester.py
eth_vertigo/interfaces/__init__.py
eth_vertigo/interfaces/generics.py
eth_vertigo/interfaces/common/__init__.py
eth_vertigo/interfaces/common/tester.py
eth_vertigo/interfaces/hardhat/__init__.py
eth_vertigo/interfaces/hardhat/compile.py
eth_vertigo/interfaces/hardhat/core.py
eth_vertigo/interfaces/hardhat/mutator.py
eth_vertigo/interfaces/hardhat/tester.py
eth_vertigo/interfaces/truffle/__init__.py
eth_vertigo/interfaces/truffle/compiler.py
eth_vertigo/interfaces/truffle/core.py
eth_vertigo/interfaces/truffle/mutator.py
eth_vertigo/interfaces/truffle/tester.py
eth_vertigo/mutator/__init__.py
eth_vertigo/mutator/mutation_configuration.py
eth_vertigo/mutator/mutator.py
eth_vertigo/mutator/source_file.py
eth_vertigo/mutator/source_mutator.py
eth_vertigo/mutator/solidity/__init__.py
eth_vertigo/mutator/solidity/solidity_file.py
eth_vertigo/mutator/solidity/solidity_mutator.py
eth_vertigo/mutator/universal_mutator/__init__.py
eth_vertigo/mutator/universal_mutator/rule.py
eth_vertigo/mutator/universal_mutator/rule_loader.py
eth_vertigo/test_runner/__init__.py
eth_vertigo/test_runner/exceptions.py
eth_vertigo/test_runner/file_editor.py
eth_vertigo/test_runner/runner.py
eth_vertigo/test_runner/test_result.py
eth_vertigo-1.3.0.dist-info/LICENSE
eth_vertigo-1.3.0.dist-info/METADATA
eth_vertigo-1.3.0.dist-info/WHEEL
eth_vertigo-1.3.0.dist-info/entry_points.txt
eth_vertigo-1.3.0.dist-info/top_level.txt
eth_vertigo-1.3.0.dist-info/RECORD
