Metadata-Version: 2.1
Name: eth-vertigo
Version: 1.3.0
Summary: Mutation Testing for Ethereum Smart Contracts
Home-page: https://github.com/joranhonig/vertigo
Author: Joran Honig
Author-email: joran.honig@gmail.com
License: GPLv3
Platform: UNKNOWN
Classifier: Programming Language :: Python :: 3
Classifier: Programming Language :: Python :: 3.7
Requires-Dist: jsonpath-rw
Requires-Dist: pytest
Requires-Dist: click
Requires-Dist: tqdm
Requires-Dist: jinja2
Requires-Dist: loguru
